<?xml version="1.0" encoding="UTF-8"?>
<!--Sample XML file generated by XMLSpy v2012 rel. 2 sp1 (http://www.altova.com)-->
<HealthExchangeErrors xsi:schemaLocation="urn:us:gov:treasury:irs:msg:hhsirsepderrorresponsedata HHS-IRS-EPDErrorResponseMessage-1.0.xsd" xmlns="urn:us:gov:treasury:irs:msg:hhsirsepderrorresponsedata" xmlns:xsi="http://www.w3.org/2001/XMLSchema-instance" xmlns:irs="urn:us:gov:treasury:irs:common">
	<irs:SubmissionYr>1000</irs:SubmissionYr>
	<irs:SubmissionMonthNum>01</irs:SubmissionMonthNum>
	<irs:ApplicableCoverageYr>1000</irs:ApplicableCoverageYr>
	<irs:BatchId>2001-12-17T09:30:47Z</irs:BatchId>
	<irs:DocumentSequenceNum>00001</irs:DocumentSequenceNum>
	<irs:BatchTransmissionQty>0</irs:BatchTransmissionQty>
	<irs:IndividualExchangeError>
		<irs:HealthExchangeId>00.AA*.000.000.000</irs:HealthExchangeId>
		<irs:IRSHouseholdErrorDtl>
			<irs:IRSGroupIdentificationNum>aaaaaaaaaaaaaaaa</irs:IRSGroupIdentificationNum>
			<irs:TaxHouseholdErrorDtl>
				<irs:TaxHouseholdCoverageErrorDtl>
					<irs:HouseholdErrorDtl>
						<irs:PrimaryInfoErrorsGrp>
							<irs:PrimaryInfoErrorDtl>
								<irs:CompletePersonNameErrorDtl>
									<irs:EPDErrorDetail>
										<irs:ErrorMessageCd>String</irs:ErrorMessageCd>
										<irs:ErrorMessageTxt>String</irs:ErrorMessageTxt>
										<irs:ErrorValueTxt>String</irs:ErrorValueTxt>
										<irs:XpathContent>String</irs:XpathContent>
									</irs:EPDErrorDetail>
								</irs:CompletePersonNameErrorDtl>
								<irs:USAddressErrorDtl>
									<irs:EPDErrorDetail>
										<irs:ErrorMessageCd>String</irs:ErrorMessageCd>
										<irs:ErrorMessageTxt>String</irs:ErrorMessageTxt>
										<irs:ErrorValueTxt>String</irs:ErrorValueTxt>
										<irs:XpathContent>String</irs:XpathContent>
									</irs:EPDErrorDetail>
								</irs:USAddressErrorDtl>
								<irs:EPDErrorDetail>
									<irs:ErrorMessageCd>String</irs:ErrorMessageCd>
									<irs:ErrorMessageTxt>String</irs:ErrorMessageTxt>
									<irs:ErrorValueTxt>String</irs:ErrorValueTxt>
									<irs:XpathContent>String</irs:XpathContent>
								</irs:EPDErrorDetail>
							</irs:PrimaryInfoErrorDtl>
							<irs:EmployerMECErrorDtl>
								<irs:BusinessNameErrorDtl>
									<irs:EPDErrorDetail>
										<irs:ErrorMessageCd>String</irs:ErrorMessageCd>
										<irs:ErrorMessageTxt>String</irs:ErrorMessageTxt>
										<irs:ErrorValueTxt>String</irs:ErrorValueTxt>
										<irs:XpathContent>String</irs:XpathContent>
									</irs:EPDErrorDetail>
								</irs:BusinessNameErrorDtl>
								<irs:BusinessAddressErrorDtl>
									<irs:USAddressErrorDtl>
										<irs:EPDErrorDetail>
											<irs:ErrorMessageCd>String</irs:ErrorMessageCd>
											<irs:ErrorMessageTxt>String</irs:ErrorMessageTxt>
											<irs:ErrorValueTxt>String</irs:ErrorValueTxt>
											<irs:XpathContent>String</irs:XpathContent>
										</irs:EPDErrorDetail>
									</irs:USAddressErrorDtl>
									<irs:EPDErrorDetail>
										<irs:ErrorMessageCd>String</irs:ErrorMessageCd>
										<irs:ErrorMessageTxt>String</irs:ErrorMessageTxt>
										<irs:ErrorValueTxt>String</irs:ErrorValueTxt>
										<irs:XpathContent>String</irs:XpathContent>
									</irs:EPDErrorDetail>
								</irs:BusinessAddressErrorDtl>
								<irs:EPDErrorDetail>
									<irs:ErrorMessageCd>String</irs:ErrorMessageCd>
									<irs:ErrorMessageTxt>String</irs:ErrorMessageTxt>
									<irs:ErrorValueTxt>String</irs:ErrorValueTxt>
									<irs:XpathContent>String</irs:XpathContent>
								</irs:EPDErrorDetail>
							</irs:EmployerMECErrorDtl>
							<irs:EPDErrorDetail>
								<irs:ErrorMessageCd>String</irs:ErrorMessageCd>
								<irs:ErrorMessageTxt>String</irs:ErrorMessageTxt>
								<irs:ErrorValueTxt>String</irs:ErrorValueTxt>
								<irs:XpathContent>String</irs:XpathContent>
							</irs:EPDErrorDetail>
						</irs:PrimaryInfoErrorsGrp>
						<irs:SpouseInfoErrorsGrp>
							<irs:SpouseInfoErrorDtl>
								<irs:CompletePersonNameErrorDtl>
									<irs:EPDErrorDetail>
										<irs:ErrorMessageCd>String</irs:ErrorMessageCd>
										<irs:ErrorMessageTxt>String</irs:ErrorMessageTxt>
										<irs:ErrorValueTxt>String</irs:ErrorValueTxt>
										<irs:XpathContent>String</irs:XpathContent>
									</irs:EPDErrorDetail>
								</irs:CompletePersonNameErrorDtl>
								<irs:EPDErrorDetail>
									<irs:ErrorMessageCd>String</irs:ErrorMessageCd>
									<irs:ErrorMessageTxt>String</irs:ErrorMessageTxt>
									<irs:ErrorValueTxt>String</irs:ErrorValueTxt>
									<irs:XpathContent>String</irs:XpathContent>
								</irs:EPDErrorDetail>
							</irs:SpouseInfoErrorDtl>
							<irs:EmployerMECErrorDtl>
								<irs:BusinessNameErrorDtl>
									<irs:EPDErrorDetail>
										<irs:ErrorMessageCd>String</irs:ErrorMessageCd>
										<irs:ErrorMessageTxt>String</irs:ErrorMessageTxt>
										<irs:ErrorValueTxt>String</irs:ErrorValueTxt>
										<irs:XpathContent>String</irs:XpathContent>
									</irs:EPDErrorDetail>
								</irs:BusinessNameErrorDtl>
								<irs:BusinessAddressErrorDtl>
									<irs:USAddressErrorDtl>
										<irs:EPDErrorDetail>
											<irs:ErrorMessageCd>String</irs:ErrorMessageCd>
											<irs:ErrorMessageTxt>String</irs:ErrorMessageTxt>
											<irs:ErrorValueTxt>String</irs:ErrorValueTxt>
											<irs:XpathContent>String</irs:XpathContent>
										</irs:EPDErrorDetail>
									</irs:USAddressErrorDtl>
									<irs:EPDErrorDetail>
										<irs:ErrorMessageCd>String</irs:ErrorMessageCd>
										<irs:ErrorMessageTxt>String</irs:ErrorMessageTxt>
										<irs:ErrorValueTxt>String</irs:ErrorValueTxt>
										<irs:XpathContent>String</irs:XpathContent>
									</irs:EPDErrorDetail>
								</irs:BusinessAddressErrorDtl>
								<irs:EPDErrorDetail>
									<irs:ErrorMessageCd>String</irs:ErrorMessageCd>
									<irs:ErrorMessageTxt>String</irs:ErrorMessageTxt>
									<irs:ErrorValueTxt>String</irs:ErrorValueTxt>
									<irs:XpathContent>String</irs:XpathContent>
								</irs:EPDErrorDetail>
							</irs:EmployerMECErrorDtl>
							<irs:EPDErrorDetail>
								<irs:ErrorMessageCd>String</irs:ErrorMessageCd>
								<irs:ErrorMessageTxt>String</irs:ErrorMessageTxt>
								<irs:ErrorValueTxt>String</irs:ErrorValueTxt>
								<irs:XpathContent>String</irs:XpathContent>
							</irs:EPDErrorDetail>
						</irs:SpouseInfoErrorsGrp>
						<irs:DependentInfoErrorsGrp>
							<irs:DependentInfoErrorDtl>
								<irs:CompletePersonNameErrorDtl>
									<irs:EPDErrorDetail>
										<irs:ErrorMessageCd>String</irs:ErrorMessageCd>
										<irs:ErrorMessageTxt>String</irs:ErrorMessageTxt>
										<irs:ErrorValueTxt>String</irs:ErrorValueTxt>
										<irs:XpathContent>String</irs:XpathContent>
									</irs:EPDErrorDetail>
								</irs:CompletePersonNameErrorDtl>
								<irs:EPDErrorDetail>
									<irs:ErrorMessageCd>String</irs:ErrorMessageCd>
									<irs:ErrorMessageTxt>String</irs:ErrorMessageTxt>
									<irs:ErrorValueTxt>String</irs:ErrorValueTxt>
									<irs:XpathContent>String</irs:XpathContent>
								</irs:EPDErrorDetail>
							</irs:DependentInfoErrorDtl>
							<irs:EmployerMECErrorDtl>
								<irs:BusinessNameErrorDtl>
									<irs:EPDErrorDetail>
										<irs:ErrorMessageCd>String</irs:ErrorMessageCd>
										<irs:ErrorMessageTxt>String</irs:ErrorMessageTxt>
										<irs:ErrorValueTxt>String</irs:ErrorValueTxt>
										<irs:XpathContent>String</irs:XpathContent>
									</irs:EPDErrorDetail>
								</irs:BusinessNameErrorDtl>
								<irs:BusinessAddressErrorDtl>
									<irs:USAddressErrorDtl>
										<irs:EPDErrorDetail>
											<irs:ErrorMessageCd>String</irs:ErrorMessageCd>
											<irs:ErrorMessageTxt>String</irs:ErrorMessageTxt>
											<irs:ErrorValueTxt>String</irs:ErrorValueTxt>
											<irs:XpathContent>String</irs:XpathContent>
										</irs:EPDErrorDetail>
									</irs:USAddressErrorDtl>
									<irs:EPDErrorDetail>
										<irs:ErrorMessageCd>String</irs:ErrorMessageCd>
										<irs:ErrorMessageTxt>String</irs:ErrorMessageTxt>
										<irs:ErrorValueTxt>String</irs:ErrorValueTxt>
										<irs:XpathContent>String</irs:XpathContent>
									</irs:EPDErrorDetail>
								</irs:BusinessAddressErrorDtl>
								<irs:EPDErrorDetail>
									<irs:ErrorMessageCd>String</irs:ErrorMessageCd>
									<irs:ErrorMessageTxt>String</irs:ErrorMessageTxt>
									<irs:ErrorValueTxt>String</irs:ErrorValueTxt>
									<irs:XpathContent>String</irs:XpathContent>
								</irs:EPDErrorDetail>
							</irs:EmployerMECErrorDtl>
							<irs:EPDErrorDetail>
								<irs:ErrorMessageCd>String</irs:ErrorMessageCd>
								<irs:ErrorMessageTxt>String</irs:ErrorMessageTxt>
								<irs:ErrorValueTxt>String</irs:ErrorValueTxt>
								<irs:XpathContent>String</irs:XpathContent>
							</irs:EPDErrorDetail>
						</irs:DependentInfoErrorsGrp>
						<irs:AssociatedPolicyErrorDtl>
							<irs:EPDErrorDetail>
								<irs:ErrorMessageCd>String</irs:ErrorMessageCd>
								<irs:ErrorMessageTxt>String</irs:ErrorMessageTxt>
								<irs:ErrorValueTxt>String</irs:ErrorValueTxt>
								<irs:XpathContent>String</irs:XpathContent>
							</irs:EPDErrorDetail>
						</irs:AssociatedPolicyErrorDtl>
						<irs:EPDErrorDetail>
							<irs:ErrorMessageCd>String</irs:ErrorMessageCd>
							<irs:ErrorMessageTxt>String</irs:ErrorMessageTxt>
							<irs:ErrorValueTxt>String</irs:ErrorValueTxt>
							<irs:XpathContent>String</irs:XpathContent>
						</irs:EPDErrorDetail>
					</irs:HouseholdErrorDtl>
					<irs:EPDErrorDetail>
						<irs:ErrorMessageCd>String</irs:ErrorMessageCd>
						<irs:ErrorMessageTxt>String</irs:ErrorMessageTxt>
						<irs:ErrorValueTxt>String</irs:ErrorValueTxt>
						<irs:XpathContent>String</irs:XpathContent>
					</irs:EPDErrorDetail>
				</irs:TaxHouseholdCoverageErrorDtl>
				<irs:EPDErrorDetail>
					<irs:ErrorMessageCd>String</irs:ErrorMessageCd>
					<irs:ErrorMessageTxt>String</irs:ErrorMessageTxt>
					<irs:ErrorValueTxt>String</irs:ErrorValueTxt>
					<irs:XpathContent>String</irs:XpathContent>
				</irs:EPDErrorDetail>
			</irs:TaxHouseholdErrorDtl>
			<irs:ExemptionErrorDtl>
				<irs:ExemptionCoverageErrorDtl>
					<irs:ExemptPersonErrorDtl>
						<irs:CompletePersonNameErrorDtl>
							<irs:EPDErrorDetail>
								<irs:ErrorMessageCd>String</irs:ErrorMessageCd>
								<irs:ErrorMessageTxt>String</irs:ErrorMessageTxt>
								<irs:ErrorValueTxt>String</irs:ErrorValueTxt>
								<irs:XpathContent>String</irs:XpathContent>
							</irs:EPDErrorDetail>
						</irs:CompletePersonNameErrorDtl>
						<irs:EPDErrorDetail>
							<irs:ErrorMessageCd>String</irs:ErrorMessageCd>
							<irs:ErrorMessageTxt>String</irs:ErrorMessageTxt>
							<irs:ErrorValueTxt>String</irs:ErrorValueTxt>
							<irs:XpathContent>String</irs:XpathContent>
						</irs:EPDErrorDetail>
					</irs:ExemptPersonErrorDtl>
					<irs:EPDErrorDetail>
						<irs:ErrorMessageCd>String</irs:ErrorMessageCd>
						<irs:ErrorMessageTxt>String</irs:ErrorMessageTxt>
						<irs:ErrorValueTxt>String</irs:ErrorValueTxt>
						<irs:XpathContent>String</irs:XpathContent>
					</irs:EPDErrorDetail>
				</irs:ExemptionCoverageErrorDtl>
				<irs:EPDErrorDetail>
					<irs:ErrorMessageCd>String</irs:ErrorMessageCd>
					<irs:ErrorMessageTxt>String</irs:ErrorMessageTxt>
					<irs:ErrorValueTxt>String</irs:ErrorValueTxt>
					<irs:XpathContent>String</irs:XpathContent>
				</irs:EPDErrorDetail>
			</irs:ExemptionErrorDtl>
			<irs:InsurancePolicyErrorDtl>
				<irs:InsuranceCoverageErrorDtl>
					<irs:CoveredIndividualErrorDtl>
						<irs:InsuredPersonErrorDtl>
							<irs:CompletePersonNameErrorDtl>
								<irs:EPDErrorDetail>
									<irs:ErrorMessageCd>String</irs:ErrorMessageCd>
									<irs:ErrorMessageTxt>String</irs:ErrorMessageTxt>
									<irs:ErrorValueTxt>String</irs:ErrorValueTxt>
									<irs:XpathContent>String</irs:XpathContent>
								</irs:EPDErrorDetail>
							</irs:CompletePersonNameErrorDtl>
							<irs:EPDErrorDetail>
								<irs:ErrorMessageCd>String</irs:ErrorMessageCd>
								<irs:ErrorMessageTxt>String</irs:ErrorMessageTxt>
								<irs:ErrorValueTxt>String</irs:ErrorValueTxt>
								<irs:XpathContent>String</irs:XpathContent>
							</irs:EPDErrorDetail>
						</irs:InsuredPersonErrorDtl>
						<irs:EPDErrorDetail>
							<irs:ErrorMessageCd>String</irs:ErrorMessageCd>
							<irs:ErrorMessageTxt>String</irs:ErrorMessageTxt>
							<irs:ErrorValueTxt>String</irs:ErrorValueTxt>
							<irs:XpathContent>String</irs:XpathContent>
						</irs:EPDErrorDetail>
					</irs:CoveredIndividualErrorDtl>
					<irs:EPDErrorDetail>
						<irs:ErrorMessageCd>String</irs:ErrorMessageCd>
						<irs:ErrorMessageTxt>String</irs:ErrorMessageTxt>
						<irs:ErrorValueTxt>String</irs:ErrorValueTxt>
						<irs:XpathContent>String</irs:XpathContent>
					</irs:EPDErrorDetail>
				</irs:InsuranceCoverageErrorDtl>
				<irs:EPDErrorDetail>
					<irs:ErrorMessageCd>String</irs:ErrorMessageCd>
					<irs:ErrorMessageTxt>String</irs:ErrorMessageTxt>
					<irs:ErrorValueTxt>String</irs:ErrorValueTxt>
					<irs:XpathContent>String</irs:XpathContent>
				</irs:EPDErrorDetail>
			</irs:InsurancePolicyErrorDtl>
			<irs:EPDErrorDetail>
				<irs:ErrorMessageCd>String</irs:ErrorMessageCd>
				<irs:ErrorMessageTxt>String</irs:ErrorMessageTxt>
				<irs:ErrorValueTxt>String</irs:ErrorValueTxt>
				<irs:XpathContent>String</irs:XpathContent>
			</irs:EPDErrorDetail>
		</irs:IRSHouseholdErrorDtl>
		<irs:EPDErrorDetail>
			<irs:ErrorMessageCd>String</irs:ErrorMessageCd>
			<irs:ErrorMessageTxt>String</irs:ErrorMessageTxt>
			<irs:ErrorValueTxt>String</irs:ErrorValueTxt>
			<irs:XpathContent>String</irs:XpathContent>
		</irs:EPDErrorDetail>
	</irs:IndividualExchangeError>
	<irs:EPDErrorDetail>
		<irs:ErrorMessageCd>String</irs:ErrorMessageCd>
		<irs:ErrorMessageTxt>String</irs:ErrorMessageTxt>
		<irs:ErrorValueTxt>String</irs:ErrorValueTxt>
		<irs:XpathContent>String</irs:XpathContent>
	</irs:EPDErrorDetail>
</HealthExchangeErrors>
